scale_lidar_io/__init__.py
scale_lidar_io/camera.py
scale_lidar_io/color_utils.py
scale_lidar_io/connectors.py
scale_lidar_io/frame.py
scale_lidar_io/helper.py
scale_lidar_io/image.py
scale_lidar_io/interpolate_transforms.py
scale_lidar_io/lidar_frame_1_pb2.py
scale_lidar_io/nucleus_scene.py
scale_lidar_io/protobuf_helper.py
scale_lidar_io/scene.py
scale_lidar_io/task.py
scale_lidar_io/transform.py
scale_lidar_io-1.2.5.dist-info/LICENSE.md
scale_lidar_io-1.2.5.dist-info/METADATA
scale_lidar_io-1.2.5.dist-info/WHEEL
scale_lidar_io-1.2.5.dist-info/top_level.txt
scale_lidar_io-1.2.5.dist-info/RECORD
