Metadata-Version: 2.1
Name: scale-lidar-io
Version: 1.2.5
Summary: Lidar data conversion helpers
Author: Scale AI
Author-email: rodrigo.belfiore@scale.com, ivan.roumec@scale.com
Classifier: Programming Language :: Python :: 3
Classifier: License :: OSI Approved :: MIT License
Classifier: Operating System :: OS Independent
Requires-Python: >=3.6
License-File: LICENSE.md
Requires-Dist: scaleapi (>=2.0.3)
Requires-Dist: pytest
Requires-Dist: pymongo
Requires-Dist: open3d
Requires-Dist: cryptography
Requires-Dist: requests
Requires-Dist: awscli
Requires-Dist: smart-open
Requires-Dist: boto3
Requires-Dist: laspy
Requires-Dist: matplotlib
Requires-Dist: numpy
Requires-Dist: opencv-python
Requires-Dist: pandas
Requires-Dist: Pillow
Requires-Dist: PyYAML
Requires-Dist: transforms3d
Requires-Dist: ujson
Requires-Dist: pyquaternion
Requires-Dist: pyntcloud
